[{"country":"AO","canton":"Uíge Province","district":"","name":"Alto Cauale","bfs":"AO-001","domain":"","provider":"unknown","has_mx":false,"reason":"No MX records found"},{"country":"AO","canton":"Moxico Province","district":"","name":"Alto Zambeze","bfs":"AO-002","domain":"","provider":"unknown","has_mx":false,"reason":"No MX records found"},{"country":"AO","canton":"Cuanza Norte Province","district":"","population":61769,"name":"Ambaca","bfs":"AO-003","domain":"","provider":"unknown","has_mx":false,"reason":"No MX records found"},{"country":"AO","canton":"Cuanza Sul Province","district":"","population":271843,"name":"Amboim","bfs":"AO-004","domain":"","provider":"unknown","has_mx":false,"reason":"No MX records found"},{"country":"AO","canton":"Bengo Province","district":"","population":17000,"name":"Ambriz","bfs":"AO-005","domain":"","provider":"unknown","has_mx":false,"reason":"No MX records found"},{"country":"AO","canton":"Uíge Province","district":"","name":"Ambuila","bfs":"AO-006","domain":"","provider":"unknown","has_mx":false,"reason":"No MX records found"},{"country":"AO","canton":"Bié Province","district":"","population":258161,"name":"Andulo","bfs":"AO-007","domain":"","provider":"unknown","has_mx":false,"reason":"No MX records found"},{"country":"AO","canton":"Huambo Province","district":"","population":294494,"name":"Bailundo","bfs":"AO-008","domain":"","provider":"unknown","has_mx":false,"reason":"No MX records found"},{"country":"AO","canton":"Benguela Province","district":"","population":108965,"name":"Balombo","bfs":"AO-009","domain":"","provider":"unknown","has_mx":false,"reason":"No MX records found"},{"country":"AO","canton":"Cuanza Norte Province","district":"","name":"Banga","bfs":"AO-010","domain":"","provider":"unknown","has_mx":false,"reason":"No MX records found"},{"country":"AO","canton":"Benguela Province","district":"","population":107841,"name":"Baía Farta","bfs":"AO-011","domain":"","provider":"unknown","has_mx":false,"reason":"No MX records found"},{"osm_relation_id":8665098,"country":"AO","canton":"Luanda Province","district":"","population":500000,"name":"Belas","bfs":"AO-012","domain":"","provider":"unknown","has_mx":false,"reason":"No MX records found"},{"country":"AO","canton":"Cabinda Province","district":"","name":"Belize","bfs":"AO-013","domain":"","provider":"unknown","has_mx":false,"reason":"No MX records found"},{"country":"AO","canton":"Uíge Province","district":"","name":"Bembe","bfs":"AO-014","domain":"","provider":"unknown","has_mx":false,"reason":"No MX records found"},{"country":"AO","canton":"Benguela Province","district":"","mx_countries":["AO"],"population":561775,"name":"Benguela","bfs":"AO-015","domain":"benguela.gov.ao","provider":"independent","has_mx":true,"mx":["mail.gov.ao"],"reason":"MX (mail.gov.ao) is self-hosted"},{"country":"AO","canton":"Namibe Province","district":"","name":"Bibala","bfs":"AO-016","domain":"","provider":"unknown","has_mx":false,"reason":"No MX records found"},{"country":"AO","canton":"Benguela Province","district":"","population":164685,"name":"Bocoio","bfs":"AO-017","domain":"","provider":"unknown","has_mx":false,"reason":"No MX records found"},{"country":"AO","canton":"Cuanza Norte Province","district":"","population":13019,"name":"Bolongongo","bfs":"AO-018","domain":"","provider":"unknown","has_mx":false,"reason":"No MX records found"},{"country":"AO","canton":"Cabinda Province","district":"","population":32792,"name":"Buco-Zau","bfs":"AO-019","domain":"","provider":"unknown","has_mx":false,"reason":"No MX records found"},{"country":"AO","canton":"Uíge Province","district":"","name":"Buengas","bfs":"AO-020","domain":"","provider":"unknown","has_mx":false,"reason":"No MX records found"},{"country":"AO","canton":"Bengo Province","district":"","population":13454,"name":"Bula Atumba","bfs":"AO-021","domain":"","provider":"unknown","has_mx":false,"reason":"No MX records found"},{"country":"AO","canton":"Moxico Province","district":"","name":"Bundas","bfs":"AO-022","domain":"","provider":"unknown","has_mx":false,"reason":"No MX records found"},{"country":"AO","canton":"Uíge Province","district":"","name":"Bungo","bfs":"AO-023","domain":"","provider":"unknown","has_mx":false,"reason":"No MX records found"},{"country":"AO","canton":"Cabinda Province","district":"","mx_countries":["AO"],"population":739182,"name":"Cabinda","bfs":"AO-024","domain":"cabinda.gov.ao","provider":"independent","has_mx":true,"mx":["mail.gov.ao"],"reason":"MX (mail.gov.ao) is self-hosted"},{"country":"AO","canton":"Huambo Province","district":"","population":120677,"name":"Cachiungo","bfs":"AO-025","domain":"","provider":"unknown","has_mx":false,"reason":"No MX records found"},{"country":"AO","canton":"Lunda Sul Province","district":"","name":"Cacolo","bfs":"AO-026","domain":"","provider":"unknown","has_mx":false,"reason":"No MX records found"},{"osm_relation_id":11162249,"country":"AO","canton":"Huíla Province","district":"","population":167820,"name":"Caconda","bfs":"AO-027","domain":"","provider":"unknown","has_mx":false,"reason":"No MX records found"},{"country":"AO","canton":"Cabinda Province","district":"","population":48801,"name":"Cacongo","bfs":"AO-028","domain":"","provider":"unknown","has_mx":false,"reason":"No MX records found"},{"osm_relation_id":11704232,"country":"AO","canton":"Luanda Province","district":"","population":1279488,"name":"Cacuaco","bfs":"AO-029","domain":"","provider":"unknown","has_mx":false,"reason":"No MX records found"},{"country":"AO","canton":"Huíla Province","district":"","name":"Cacula","bfs":"AO-030","domain":"","provider":"unknown","has_mx":false,"reason":"No MX records found"},{"country":"AO","canton":"Malanje Province","district":"","name":"Cacuso","bfs":"AO-031","domain":"","provider":"unknown","has_mx":false,"reason":"No MX records found"},{"country":"AO","canton":"Cunene Province","district":"","population":70061,"name":"Cahama","bfs":"AO-032","domain":"","provider":"unknown","has_mx":false,"reason":"No MX records found"},{"country":"AO","canton":"Benguela Province","district":"","population":90838,"name":"Caimbambo","bfs":"AO-033","domain":"","provider":"unknown","has_mx":false,"reason":"No MX records found"},{"country":"AO","canton":"Cuando Cubango Province","district":"","population":22654,"name":"Calai","bfs":"AO-034","domain":"","provider":"unknown","has_mx":false,"reason":"No MX records found"},{"osm_relation_id":2822141,"country":"AO","canton":"Malanje Province","district":"","name":"Calandula","bfs":"AO-035","domain":"","provider":"unknown","has_mx":false,"reason":"No MX records found"},{"osm_relation_id":11162246,"country":"AO","canton":"Huíla Province","district":"","population":169420,"name":"Caluquembe","bfs":"AO-036","domain":"","provider":"unknown","has_mx":false,"reason":"No MX records found"},{"country":"AO","canton":"Namibe Province","district":"","name":"Camacuio","bfs":"AO-037","domain":"","provider":"unknown","has_mx":false,"reason":"No MX records found"},{"country":"AO","canton":"Bié Province","district":"","population":19150,"name":"Camacupa","bfs":"AO-038","domain":"","provider":"unknown","has_mx":false,"reason":"No MX records found"},{"country":"AO","canton":"Moxico Province","district":"","name":"Camanongue","bfs":"AO-039","domain":"","provider":"unknown","has_mx":false,"reason":"No MX records found"},{"country":"AO","canton":"Cuanza Norte Province","district":"","population":90766,"name":"Cambambe","bfs":"AO-040","domain":"","provider":"unknown","has_mx":false,"reason":"No MX records found"},{"country":"AO","canton":"Lunda Norte Province","district":"","name":"Cambulo","bfs":"AO-041","domain":"","provider":"unknown","has_mx":false,"reason":"No MX records found"},{"country":"AO","canton":"Malanje Province","district":"","name":"Cambundi-Catembo","bfs":"AO-042","domain":"","provider":"unknown","has_mx":false,"reason":"No MX records found"},{"country":"AO","canton":"Moxico Province","district":"","name":"Cameia","bfs":"AO-043","domain":"","provider":"unknown","has_mx":false,"reason":"No MX records found"},{"country":"AO","canton":"Moxico Province","district":"","name":"Cangamba","bfs":"AO-044","domain":"","provider":"unknown","has_mx":false,"reason":"No MX records found"},{"country":"AO","canton":"Malanje Province","district":"","name":"Cangandala","bfs":"AO-045","domain":"","provider":"unknown","has_mx":false,"reason":"No MX records found"},{"country":"AO","canton":"Lunda Norte Province","district":"","name":"Caombo","bfs":"AO-046","domain":"","provider":"unknown","has_mx":false,"reason":"No MX records found"},{"country":"AO","canton":"Lunda Norte Province","district":"","name":"Capenda-Camulemba","bfs":"AO-047","domain":"","provider":"unknown","has_mx":false,"reason":"No MX records found"},{"country":"AO","canton":"Cuanza Sul Province","district":"","population":117000,"name":"Cassongue","bfs":"AO-048","domain":"","provider":"unknown","has_mx":false,"reason":"No MX records found"},{"country":"AO","canton":"Bié Province","district":"","population":126631,"name":"Catabola","bfs":"AO-049","domain":"","provider":"unknown","has_mx":false,"reason":"No MX records found"},{"country":"AO","canton":"Benguela Province","district":"","population":175805,"name":"Catumbela","bfs":"AO-050","domain":"","provider":"unknown","has_mx":false,"reason":"No MX records found"},{"country":"AO","canton":"Lunda Norte Province","district":"","population":28164,"name":"Caungula","bfs":"AO-051","domain":"","provider":"unknown","has_mx":false,"reason":"No MX records found"},{"osm_relation_id":11704228,"country":"AO","canton":"Luanda Province","district":"","name":"Cazenga","bfs":"AO-052","domain":"cazenga.gov.ao","provider":"independent","has_mx":true,"mx":["smtp3.cazenga.gov.ao"],"reason":"MX (smtp3.cazenga.gov.ao) is self-hosted"},{"country":"AO","canton":"Cuanza Norte Province","district":"","population":171743,"name":"Cazengo","bfs":"AO-053","domain":"","provider":"unknown","has_mx":false,"reason":"No MX records found"},{"country":"AO","canton":"Huambo Province","district":"","population":279792,"name":"Caála","bfs":"AO-054","domain":"","provider":"unknown","has_mx":false,"reason":"No MX records found"},{"country":"AO","canton":"Cuanza Sul Province","district":"","name":"Cela","bfs":"AO-055","domain":"","provider":"unknown","has_mx":false,"reason":"No MX records found"},{"osm_relation_id":11162242,"country":"AO","canton":"Huíla Province","district":"","population":190670,"name":"Chibia","bfs":"AO-056","domain":"chibia.com","provider":"unknown","has_mx":false,"reason":"No MX records found"},{"country":"AO","canton":"Huambo Province","district":"","population":103646,"name":"Chicala-Choloanga","bfs":"AO-057","domain":"","provider":"unknown","has_mx":false,"reason":"No MX records found"},{"osm_relation_id":11162248,"country":"AO","canton":"Huíla Province","district":"","population":131807,"name":"Chicomba","bfs":"AO-058","domain":"","provider":"unknown","has_mx":false,"reason":"No MX records found"},{"country":"AO","canton":"Bié Province","district":"","population":129370,"name":"Chinguar","bfs":"AO-059","domain":"","provider":"unknown","has_mx":false,"reason":"No MX records found"},{"osm_relation_id":11162250,"country":"AO","canton":"Huíla Province","district":"","population":64714,"name":"Chipindo","bfs":"AO-060","domain":"","provider":"unknown","has_mx":false,"reason":"No MX records found"},{"country":"AO","canton":"Lunda Norte Province","district":"","population":195136,"name":"Chitato","bfs":"AO-061","domain":"","provider":"unknown","has_mx":false,"reason":"No MX records found"},{"country":"AO","canton":"Bié Province","district":"","population":78156,"name":"Chitembo","bfs":"AO-062","domain":"","provider":"unknown","has_mx":false,"reason":"No MX records found"},{"country":"AO","canton":"Benguela Province","district":"","population":87278,"name":"Chongorói","bfs":"AO-063","domain":"","provider":"unknown","has_mx":false,"reason":"No MX records found"},{"country":"AO","canton":"Cuanza Sul Province","district":"","population":89479,"name":"Conda","bfs":"AO-064","domain":"","provider":"unknown","has_mx":false,"reason":"No MX records found"},{"country":"AO","canton":"Malanje Province","district":"","name":"Cuaba Nzogo","bfs":"AO-065","domain":"","provider":"unknown","has_mx":false,"reason":"No MX records found"},{"country":"AO","canton":"Cuando Cubango Province","district":"","population":28459,"name":"Cuangar","bfs":"AO-066","domain":"","provider":"unknown","has_mx":false,"reason":"No MX records found"},{"country":"AO","canton":"Lunda Norte Province","district":"","population":183767,"name":"Cuango","bfs":"AO-067","domain":"","provider":"unknown","has_mx":false,"reason":"No MX records found"},{"country":"AO","canton":"Benguela Province","district":"","population":357618,"name":"Cubal","bfs":"AO-068","domain":"","provider":"unknown","has_mx":false,"reason":"No MX records found"},{"country":"AO","canton":"Cuando Cubango Province","district":"","population":42974,"name":"Cuchi","bfs":"AO-069","domain":"","provider":"unknown","has_mx":false,"reason":"No MX records found"},{"country":"AO","canton":"Bié Province","district":"","population":56963,"name":"Cuemba","bfs":"AO-070","domain":"","provider":"unknown","has_mx":false,"reason":"No MX records found"},{"country":"AO","canton":"Lunda Norte Province","district":"","population":21004,"name":"Cuilo","bfs":"AO-071","domain":"","provider":"unknown","has_mx":false,"reason":"No MX records found"},{"country":"AO","canton":"Zaire Province","district":"","name":"Cuimba","bfs":"AO-072","domain":"","provider":"unknown","has_mx":false,"reason":"No MX records found"},{"country":"AO","canton":"Cuando Cubango Province","district":"","population":40829,"name":"Cuito Cuanavale","bfs":"AO-073","domain":"","provider":"unknown","has_mx":false,"reason":"No MX records found"},{"country":"AO","canton":"Malanje Province","district":"","name":"Cunda-Dia-Baze","bfs":"AO-074","domain":"","provider":"unknown","has_mx":false,"reason":"No MX records found"},{"country":"AO","canton":"Bié Province","district":"","population":73826,"name":"Cunhinga","bfs":"AO-075","domain":"","provider":"unknown","has_mx":false,"reason":"No MX records found"},{"country":"AO","canton":"Lunda Sul Province","district":"","name":"Dala","bfs":"AO-076","domain":"","provider":"unknown","has_mx":false,"reason":"No MX records found"},{"country":"AO","canton":"Uíge Province","district":"","name":"Damba","bfs":"AO-077","domain":"","provider":"unknown","has_mx":false,"reason":"No MX records found"},{"country":"AO","canton":"Bengo Province","district":"","population":222528,"name":"Dande","bfs":"AO-078","domain":"","provider":"unknown","has_mx":false,"reason":"No MX records found"},{"country":"AO","canton":"Bengo Province","district":"","population":30058,"name":"Dembos","bfs":"AO-079","domain":"","provider":"unknown","has_mx":false,"reason":"No MX records found"},{"country":"AO","canton":"Cuando Cubango Province","district":"","population":15126,"name":"Dirico","bfs":"AO-080","domain":"","provider":"unknown","has_mx":false,"reason":"No MX records found"},{"country":"AO","canton":"Cuanza Sul Province","district":"","name":"Ebo","bfs":"AO-081","domain":"","provider":"unknown","has_mx":false,"reason":"No MX records found"},{"country":"AO","canton":"Huambo Province","district":"","name":"Ecunha","bfs":"AO-082","domain":"","provider":"unknown","has_mx":false,"reason":"No MX records found"},{"country":"AO","canton":"Huíla Province","district":"","name":"Gambos","bfs":"AO-083","domain":"","provider":"unknown","has_mx":false,"reason":"No MX records found"},{"country":"AO","canton":"Benguela Province","district":"","population":235486,"name":"Ganda","bfs":"AO-084","domain":"","provider":"unknown","has_mx":false,"reason":"No MX records found"},{"country":"AO","canton":"Cuanza Norte Province","district":"","name":"Golungo Alto","bfs":"AO-085","domain":"","provider":"unknown","has_mx":false,"reason":"No MX records found"},{"country":"AO","canton":"Cuanza Norte Province","district":"","name":"Gonguembo","bfs":"AO-086","domain":"","provider":"unknown","has_mx":false,"reason":"No MX records found"},{"country":"AO","canton":"Huambo Province","district":"","mx_countries":["AO"],"population":844000,"name":"Huambo","bfs":"AO-087","domain":"huambo.gov.ao","provider":"independent","has_mx":true,"mx":["mail.gov.ao"],"reason":"MX (mail.gov.ao) is self-hosted"},{"osm_relation_id":11162240,"country":"AO","canton":"Huíla Province","district":"","population":89144,"name":"Humpata","bfs":"AO-088","domain":"","provider":"unknown","has_mx":false,"reason":"No MX records found"},{"osm_relation_id":11162252,"country":"AO","canton":"Huíla Province","district":"","population":105090,"name":"Jamba","bfs":"AO-089","domain":"","provider":"unknown","has_mx":false,"reason":"No MX records found"},{"country":"AO","canton":"Bié Province","district":"","population":512706,"name":"Kuito","bfs":"AO-090","domain":"","provider":"unknown","has_mx":false,"reason":"No MX records found"},{"country":"AO","canton":"Cunene Province","district":"","population":41087,"name":"Kuroka","bfs":"AO-091","domain":"","provider":"unknown","has_mx":false,"reason":"No MX records found"},{"osm_relation_id":11162251,"country":"AO","canton":"Huíla Province","district":"","population":78543,"name":"Kuvango","bfs":"AO-092","domain":"","provider":"unknown","has_mx":false,"reason":"No MX records found"},{"country":"AO","canton":"Cunene Province","district":"","population":57398,"name":"Kuvelai","bfs":"AO-093","domain":"","provider":"unknown","has_mx":false,"reason":"No MX records found"},{"country":"AO","canton":"Cunene Province","district":"","name":"Kwanyama","bfs":"AO-094","domain":"","provider":"unknown","has_mx":false,"reason":"No MX records found"},{"country":"AO","canton":"Cuanza Sul Province","district":"","mx_countries":["PT"],"name":"Libolo","bfs":"AO-095","domain":"kalulo.com","provider":"independent","has_mx":true,"mx":["kalulo.com"],"reason":"MX (kalulo.com) is self-hosted"},{"country":"AO","canton":"Benguela Province","district":"","population":436467,"name":"Lobito","bfs":"AO-096","domain":"","provider":"unknown","has_mx":false,"reason":"No MX records found"},{"country":"AO","canton":"Huambo Province","district":"","population":134254,"name":"Londuimbali","bfs":"AO-097","domain":"","provider":"unknown","has_mx":false,"reason":"No MX records found"},{"country":"AO","canton":"Huambo Province","district":"","population":86795,"name":"Longonjo","bfs":"AO-098","domain":"","provider":"unknown","has_mx":false,"reason":"No MX records found"},{"country":"AO","canton":"Moxico Leste","district":"","name":"Lovua","bfs":"AO-099","domain":"","provider":"unknown","has_mx":false,"reason":"No MX records found"},{"country":"AO","canton":"Moxico Province","district":"","name":"Luacano","bfs":"AO-100","domain":"","provider":"unknown","has_mx":false,"reason":"No MX records found"},{"osm_relation_id":11704226,"country":"AO","canton":"Luanda Province","district":"","mx_countries":["AO"],"population":2487444,"name":"Luanda Municipality","bfs":"AO-101","domain":"luanda.gov.ao","provider":"independent","has_mx":true,"mx":["mail.gov.ao"],"reason":"MX (mail.gov.ao) is self-hosted"},{"country":"AO","canton":"Moxico Leste","district":"","population":90000,"name":"Luau","bfs":"AO-102","domain":"","provider":"unknown","has_mx":false,"reason":"No MX records found"},{"country":"AO","canton":"Lunda Norte Province","district":"","population":20631,"name":"Lubalo","bfs":"AO-103","domain":"","provider":"unknown","has_mx":false,"reason":"No MX records found"},{"country":"AO","canton":"Huíla Province","district":"","population":903564,"name":"Lubango","bfs":"AO-104","domain":"","provider":"unknown","has_mx":false,"reason":"No MX records found"},{"country":"AO","canton":"Cuanza Norte Province","district":"","name":"Lucala","bfs":"AO-105","domain":"","provider":"unknown","has_mx":false,"reason":"No MX records found"},{"country":"AO","canton":"Lunda Norte Province","district":"","population":154305,"name":"Lucapa","bfs":"AO-106","domain":"","provider":"unknown","has_mx":false,"reason":"No MX records found"},{"country":"AO","canton":"Malanje Province","district":"","name":"Luquembo","bfs":"AO-107","domain":"","provider":"unknown","has_mx":false,"reason":"No MX records found"},{"country":"AO","canton":"Moxico Province","district":"","name":"Léua","bfs":"AO-108","domain":"","provider":"unknown","has_mx":false,"reason":"No MX records found"},{"country":"AO","canton":"Lunda Norte Province","district":"","population":15124,"name":"Lóvua","bfs":"AO-109","domain":"","provider":"unknown","has_mx":false,"reason":"No MX records found"},{"country":"AO","canton":"Moxico Leste","district":"","name":"Macondo","bfs":"AO-110","domain":"","provider":"unknown","has_mx":false,"reason":"No MX records found"},{"country":"AO","canton":"Malanje Province","district":"","mx_countries":["AO"],"population":604215,"name":"Malanje","bfs":"AO-111","domain":"malanje.gov.ao","provider":"independent","has_mx":true,"mx":["mail.gov.ao"],"reason":"MX (mail.gov.ao) is self-hosted"},{"country":"AO","canton":"Uíge Province","district":"","name":"Maquela do Zombo","bfs":"AO-112","domain":"","provider":"unknown","has_mx":false,"reason":"No MX records found"},{"country":"AO","canton":"Malanje Province","district":"","population":30086,"name":"Marimba","bfs":"AO-113","domain":"","provider":"unknown","has_mx":false,"reason":"No MX records found"},{"country":"AO","canton":"Cuanza Norte Province","district":"","population":24000,"name":"Massangano","bfs":"AO-114","domain":"","provider":"unknown","has_mx":false,"reason":"No MX records found"},{"country":"AO","canton":"Malanje Province","district":"","name":"Massango","bfs":"AO-115","domain":"","provider":"unknown","has_mx":false,"reason":"No MX records found"},{"osm_relation_id":11162244,"country":"AO","canton":"Huíla Province","district":"","population":262763,"name":"Matala","bfs":"AO-116","domain":"","provider":"unknown","has_mx":false,"reason":"No MX records found"},{"country":"AO","canton":"Cuando Cubango Province","district":"","population":27196,"name":"Mavinga","bfs":"AO-117","domain":"","provider":"unknown","has_mx":false,"reason":"No MX records found"},{"country":"AO","canton":"Zaire Province","district":"","name":"Mbanza Congo","bfs":"AO-118","domain":"","provider":"unknown","has_mx":false,"reason":"No MX records found"},{"country":"AO","canton":"Cuando Cubango Province","district":"","population":372500,"name":"Menongue","bfs":"AO-119","domain":"","provider":"unknown","has_mx":false,"reason":"No MX records found"},{"country":"AO","canton":"Uíge Province","district":"","name":"Milunga","bfs":"AO-120","domain":"","provider":"unknown","has_mx":false,"reason":"No MX records found"},{"country":"AO","canton":"Moxico Province","district":"","mx_countries":["AO"],"name":"Moxico","bfs":"AO-121","domain":"moxico.gov.ao","provider":"independent","has_mx":true,"mx":["mail.gov.ao"],"reason":"MX (mail.gov.ao) is self-hosted"},{"country":"AO","canton":"Uíge Province","district":"","name":"Mucaba","bfs":"AO-122","domain":"","provider":"unknown","has_mx":false,"reason":"No MX records found"},{"country":"AO","canton":"Malanje Province","district":"","name":"Mucari","bfs":"AO-123","domain":"","provider":"unknown","has_mx":false,"reason":"No MX records found"},{"country":"AO","canton":"Lunda Sul Province","district":"","name":"Muconda","bfs":"AO-124","domain":"","provider":"unknown","has_mx":false,"reason":"No MX records found"},{"country":"AO","canton":"Huambo Province","district":"","population":113417,"name":"Mungo","bfs":"AO-125","domain":"","provider":"unknown","has_mx":false,"reason":"No MX records found"},{"country":"AO","canton":"Cuanza Sul Province","district":"","population":82544,"name":"Mussende","bfs":"AO-126","domain":"","provider":"unknown","has_mx":false,"reason":"No MX records found"},{"country":"AO","canton":"Zaire Province","district":"","population":11633,"name":"N'zeto","bfs":"AO-127","domain":"","provider":"unknown","has_mx":false,"reason":"No MX records found"},{"country":"AO","canton":"Cunene Province","district":"","population":142047,"name":"Namakunde","bfs":"AO-128","domain":"","provider":"unknown","has_mx":false,"reason":"No MX records found"},{"country":"AO","canton":"Bengo Province","district":"","population":60883,"name":"Nambuangongo","bfs":"AO-129","domain":"","provider":"unknown","has_mx":false,"reason":"No MX records found"},{"country":"AO","canton":"Namibe Province","district":"","mx_countries":["AO"],"name":"Namibe","bfs":"AO-130","domain":"namibe.gov.ao","provider":"independent","has_mx":true,"mx":["mail.gov.ao"],"reason":"MX (mail.gov.ao) is self-hosted"},{"country":"AO","canton":"Cuando Cubango Province","district":"","population":2796,"name":"Nancova","bfs":"AO-131","domain":"","provider":"unknown","has_mx":false,"reason":"No MX records found"},{"country":"AO","canton":"Uíge Province","district":"","population":137559,"name":"Negage","bfs":"AO-132","domain":"","provider":"unknown","has_mx":false,"reason":"No MX records found"},{"country":"AO","canton":"Bié Province","district":"","population":126339,"name":"Nharea","bfs":"AO-133","domain":"","provider":"unknown","has_mx":false,"reason":"No MX records found"},{"country":"AO","canton":"Zaire Province","district":"","name":"Noqui","bfs":"AO-134","domain":"","provider":"unknown","has_mx":false,"reason":"No MX records found"},{"country":"AO","canton":"Cunene Province","district":"","population":304964,"name":"Ombadja","bfs":"AO-135","domain":"","provider":"unknown","has_mx":false,"reason":"No MX records found"},{"country":"AO","canton":"Bengo Province","district":"","name":"Pango Aluquém","bfs":"AO-136","domain":"","provider":"unknown","has_mx":false,"reason":"No MX records found"},{"country":"AO","canton":"Cuanza Sul Province","district":"","population":137000,"name":"Porto Amboim","bfs":"AO-137","domain":"","provider":"unknown","has_mx":false,"reason":"No MX records found"},{"country":"AO","canton":"Uíge Province","district":"","name":"Puri","bfs":"AO-138","domain":"","provider":"unknown","has_mx":false,"reason":"No MX records found"},{"country":"AO","canton":"Cuando Cubango Province","district":"","population":33053,"name":"Rivungo","bfs":"AO-139","domain":"","provider":"unknown","has_mx":false,"reason":"No MX records found"},{"country":"AO","canton":"Cuanza Norte Province","district":"","name":"Samba Cajú","bfs":"AO-140","domain":"","provider":"unknown","has_mx":false,"reason":"No MX records found"},{"country":"AO","canton":"Uíge Province","district":"","name":"Sanza Pombo","bfs":"AO-141","domain":"","provider":"unknown","has_mx":false,"reason":"No MX records found"},{"country":"AO","canton":"Lunda Sul Province","district":"","population":393000,"name":"Saurimo","bfs":"AO-142","domain":"","provider":"unknown","has_mx":false,"reason":"No MX records found"},{"country":"AO","canton":"Cuanza Sul Province","district":"","population":187127,"name":"Seles","bfs":"AO-143","domain":"","provider":"unknown","has_mx":false,"reason":"No MX records found"},{"country":"AO","canton":"Uíge Province","district":"","name":"Songo","bfs":"AO-144","domain":"","provider":"unknown","has_mx":false,"reason":"No MX records found"},{"country":"AO","canton":"Zaire Province","district":"","population":200920,"name":"Soyo","bfs":"AO-145","domain":"","provider":"unknown","has_mx":false,"reason":"No MX records found"},{"country":"AO","canton":"Cuanza Sul Province","district":"","population":279968,"name":"Sumbe","bfs":"AO-146","domain":"","provider":"unknown","has_mx":false,"reason":"No MX records found"},{"osm_relation_id":11704229,"isp_name":"Hetzner (DE)","country":"AO","canton":"Luanda Province","district":"","mx_countries":["DE"],"population":500000,"name":"Talatona","bfs":"AO-147","domain":"talatona.ao","provider":"local-isp","has_mx":true,"mx":["talatona.ao"],"reason":"MX (talatona.ao) hosted on Local ISP (Hetzner (DE))"},{"country":"AO","canton":"Huambo Province","district":"","population":30443,"name":"Tchindjenje","bfs":"AO-148","domain":"","provider":"unknown","has_mx":false,"reason":"No MX records found"},{"country":"AO","canton":"Zaire Province","district":"","name":"Tomboco","bfs":"AO-149","domain":"","provider":"unknown","has_mx":false,"reason":"No MX records found"},{"country":"AO","canton":"Namibe Province","district":"","name":"Tômbua","bfs":"AO-150","domain":"","provider":"unknown","has_mx":false,"reason":"No MX records found"},{"country":"AO","canton":"Huambo Province","district":"","population":55054,"name":"Ucuma","bfs":"AO-151","domain":"","provider":"unknown","has_mx":false,"reason":"No MX records found"},{"country":"AO","canton":"Uíge Province","district":"","mx_countries":["AO"],"population":599000,"name":"Uíge","bfs":"AO-152","domain":"uige.gov.ao","provider":"independent","has_mx":true,"mx":["mail.gov.ao"],"reason":"MX (mail.gov.ao) is self-hosted"},{"osm_relation_id":11704230,"country":"AO","canton":"Luanda Province","district":"","name":"Viana","bfs":"AO-153","domain":"","provider":"unknown","has_mx":false,"reason":"No MX records found"},{"country":"AO","canton":"Namibe Province","district":"","name":"Virei","bfs":"AO-154","domain":"","provider":"unknown","has_mx":false,"reason":"No MX records found"},{"country":"AO","canton":"","district":"","name":"Xandele","bfs":"AO-155","domain":"","provider":"unknown","has_mx":false,"reason":"No MX records found"},{"osm_relation_id":11796197,"country":"AO","canton":"Lunda Norte Province","district":"","name":"Xá-Muteba","bfs":"AO-156","domain":"","provider":"unknown","has_mx":false,"reason":"No MX records found"},{"osm_relation_id":11704233,"country":"AO","canton":"Luanda Province","district":"","population":59000,"name":"Ícolo e Bengo","bfs":"AO-157","domain":"","provider":"unknown","has_mx":false,"reason":"No MX records found"},{"country":"AO","canton":"Cabinda Province","district":"","name":"Angoio","bfs":"AO-158","domain":"","provider":"unknown","has_mx":false,"reason":"No MX records found"},{"country":"AO","canton":"Cabinda Province","district":"","name":"Liambo","bfs":"AO-159","domain":"","provider":"unknown","has_mx":false,"reason":"No MX records found"},{"country":"AO","canton":"Luanda Province","district":"","name":"Mulenvos","bfs":"AO-160","domain":"","provider":"unknown","has_mx":false,"reason":"No MX records found"},{"country":"AO","canton":"Bengo Province","district":"","name":"Panguila","bfs":"AO-161","domain":"","provider":"unknown","has_mx":false,"reason":"No MX records found"},{"country":"AO","canton":"Icolo e Bengo","district":"","name":"Sequele","bfs":"AO-162","domain":"","provider":"unknown","has_mx":false,"reason":"No MX records found"}]