[{"bfs":"SR-001","osm_relation_id":13011677,"district":"","population":5247,"provider":"unknown","domain":"","country":"SR","name":"Albina","canton":"Marowijne District","has_mx":false,"reason":"No MX records found"},{"bfs":"SR-002","district":"","provider":"unknown","domain":"","country":"SR","name":"Alkmaar","canton":"Commewijne District","has_mx":false,"reason":"No MX records found"},{"bfs":"SR-003","district":"","provider":"unknown","domain":"","country":"SR","name":"Bakkie","canton":"Commewijne District","has_mx":false,"reason":"No MX records found"},{"bfs":"SR-004","osm_relation_id":13028393,"district":"","population":17185,"provider":"unknown","domain":"","country":"SR","name":"Beekhuizen","canton":"Paramaribo District","has_mx":false,"reason":"No MX records found"},{"bfs":"SR-005","district":"","provider":"unknown","domain":"","country":"SR","name":"Bigi Poika Ressort","canton":"Para District","has_mx":false,"reason":"No MX records found"},{"bfs":"SR-006","osm_relation_id":13026222,"district":"","provider":"unknown","domain":"","country":"SR","name":"Blauwgrond","canton":"Paramaribo District","has_mx":false,"reason":"No MX records found"},{"bfs":"SR-007","osm_relation_id":12999287,"district":"","provider":"unknown","domain":"","country":"SR","name":"Boven Coppename","canton":"Sipaliwini District","has_mx":false,"reason":"No MX records found"},{"bfs":"SR-008","district":"","provider":"unknown","domain":"","country":"SR","name":"Boven Saramacca","canton":"Sipaliwini District","has_mx":false,"reason":"No MX records found"},{"bfs":"SR-009","osm_relation_id":13000342,"district":"","provider":"unknown","domain":"","country":"SR","name":"Boven Suriname","canton":"Sipaliwini District","has_mx":false,"reason":"No MX records found"},{"bfs":"SR-010","district":"","provider":"unknown","domain":"","country":"SR","name":"Brokopondo Ressort","canton":"Brokopondo District","has_mx":false,"reason":"No MX records found"},{"bfs":"SR-011","osm_relation_id":13024887,"district":"","population":4793,"provider":"unknown","domain":"","country":"SR","name":"Brownsweg","canton":"Brokopondo District","has_mx":false,"reason":"No MX records found"},{"bfs":"SR-012","osm_relation_id":13025375,"district":"","provider":"unknown","domain":"","country":"SR","name":"Calcutta","canton":"Saramacca District","has_mx":false,"reason":"No MX records found"},{"bfs":"SR-013","district":"","provider":"unknown","domain":"","country":"SR","name":"Carolina","canton":"Para District","has_mx":false,"reason":"No MX records found"},{"bfs":"SR-014","district":"","provider":"unknown","domain":"","country":"SR","name":"Centrum","canton":"Brokopondo District","has_mx":false,"reason":"No MX records found"},{"bfs":"SR-015","district":"","provider":"unknown","domain":"","country":"SR","name":"Centrum","canton":"Paramaribo District","has_mx":false,"reason":"No MX records found"},{"bfs":"SR-016","osm_relation_id":12998891,"district":"","provider":"unknown","domain":"","country":"SR","name":"Curuni","canton":"Sipaliwini District","has_mx":false,"reason":"No MX records found"},{"bfs":"SR-017","osm_relation_id":13025893,"district":"","provider":"unknown","domain":"","country":"SR","name":"De Nieuwe Grond","canton":"Wanica District","has_mx":false,"reason":"No MX records found"},{"bfs":"SR-018","district":"","provider":"unknown","domain":"","country":"SR","name":"Domburg Ressort","canton":"Wanica District","has_mx":false,"reason":"No MX records found"},{"bfs":"SR-019","osm_relation_id":13028363,"district":"","provider":"unknown","domain":"","country":"SR","name":"Flora","canton":"Paramaribo District","has_mx":false,"reason":"No MX records found"},{"bfs":"SR-020","district":"","population":741,"provider":"unknown","domain":"","country":"SR","name":"Galibi","canton":"Marowijne District","has_mx":false,"reason":"No MX records found"},{"bfs":"SR-021","district":"","provider":"unknown","domain":"","country":"SR","name":"Groningen Ressort","canton":"Saramacca District","has_mx":false,"reason":"No MX records found"},{"bfs":"SR-022","district":"","provider":"unknown","domain":"","country":"SR","name":"Groot Henar","canton":"Nickerie District","has_mx":false,"reason":"No MX records found"},{"bfs":"SR-023","osm_relation_id":13025682,"district":"","provider":"unknown","domain":"","country":"SR","name":"Houttuin","canton":"Wanica District","has_mx":false,"reason":"No MX records found"},{"bfs":"SR-024","district":"","provider":"unknown","domain":"","country":"SR","name":"Jarikaba","canton":"Saramacca District","has_mx":false,"reason":"No MX records found"},{"bfs":"SR-025","osm_relation_id":12998259,"district":"","provider":"unknown","domain":"","country":"SR","name":"Kabalebo","canton":"Sipaliwini District","has_mx":false,"reason":"No MX records found"},{"bfs":"SR-026","district":"","provider":"unknown","domain":"","country":"SR","name":"Kampong Baroe","canton":"Saramacca District","has_mx":false,"reason":"No MX records found"},{"bfs":"SR-027","district":"","provider":"unknown","domain":"","country":"SR","name":"Klaaskreek","canton":"Brokopondo District","has_mx":false,"reason":"No MX records found"},{"bfs":"SR-028","osm_relation_id":13025975,"district":"","provider":"unknown","domain":"","country":"SR","name":"Koewarasan","canton":"Wanica District","has_mx":false,"reason":"No MX records found"},{"bfs":"SR-029","district":"","provider":"unknown","domain":"","country":"SR","name":"Kwakoegron Ressort","canton":"Brokopondo District","has_mx":false,"reason":"No MX records found"},{"bfs":"SR-030","district":"","population":29526,"provider":"unknown","domain":"","country":"SR","name":"Latour","canton":"Paramaribo District","has_mx":false,"reason":"No MX records found"},{"bfs":"SR-031","osm_relation_id":13025491,"district":"","population":19991,"provider":"unknown","domain":"","country":"SR","name":"Lelydorp","canton":"Wanica District","has_mx":false,"reason":"No MX records found"},{"bfs":"SR-032","osm_relation_id":13028404,"district":"","population":8209,"provider":"unknown","domain":"","country":"SR","name":"Livorno","canton":"Paramaribo District","has_mx":false,"reason":"No MX records found"},{"bfs":"SR-033","district":"","provider":"unknown","domain":"","country":"SR","name":"Maretraite Ressort","canton":"Paramaribo District","has_mx":false,"reason":"No MX records found"},{"bfs":"SR-034","osm_relation_id":13017670,"district":"","provider":"unknown","domain":"","country":"SR","name":"Margaretha","canton":"Commewijne District","has_mx":false,"reason":"No MX records found"},{"bfs":"SR-035","osm_relation_id":13005000,"district":"","population":1171,"provider":"unknown","domain":"","country":"SR","name":"Maréchalkreek","canton":"Brokopondo District","has_mx":false,"reason":"No MX records found"},{"bfs":"SR-036","district":"","population":12405,"provider":"unknown","domain":"","country":"SR","name":"Meerzorg","canton":"Commewijne District","has_mx":false,"reason":"No MX records found"},{"bfs":"SR-037","district":"","provider":"unknown","domain":"","country":"SR","name":"Moengo Ressort","canton":"Marowijne District","has_mx":false,"reason":"No MX records found"},{"bfs":"SR-038","district":"","provider":"unknown","domain":"","country":"SR","name":"Moengotapoe","canton":"Marowijne District","has_mx":false,"reason":"No MX records found"},{"bfs":"SR-039","osm_relation_id":13026300,"district":"","provider":"unknown","domain":"","country":"SR","name":"Munder","canton":"Paramaribo District","has_mx":false,"reason":"No MX records found"},{"bfs":"SR-040","district":"","population":5650,"provider":"unknown","domain":"","country":"SR","name":"Nieuw Amsterdam","canton":"Commewijne District","has_mx":false,"reason":"No MX records found"},{"bfs":"SR-041","district":"","provider":"unknown","domain":"","country":"SR","name":"Nieuw Nickerie Ressort","canton":"Nickerie District","has_mx":false,"reason":"No MX records found"},{"bfs":"SR-042","district":"","provider":"unknown","domain":"","country":"SR","name":"Noord-Para","canton":"Para District","has_mx":false,"reason":"No MX records found"},{"bfs":"SR-043","osm_relation_id":13008877,"district":"","provider":"unknown","domain":"","country":"SR","name":"Oost-Para","canton":"Para District","has_mx":false,"reason":"No MX records found"},{"bfs":"SR-044","osm_relation_id":12996359,"district":"","provider":"unknown","domain":"","country":"SR","name":"Oostelijke Polders","canton":"Nickerie District","has_mx":false,"reason":"No MX records found"},{"bfs":"SR-045","district":"","provider":"unknown","domain":"","country":"SR","name":"Paramacca","canton":"Sipaliwini District","has_mx":false,"reason":"No MX records found"},{"bfs":"SR-046","district":"","provider":"unknown","domain":"","country":"SR","name":"Patamacca","canton":"Marowijne District","has_mx":false,"reason":"No MX records found"},{"bfs":"SR-047","osm_relation_id":13028468,"district":"","provider":"unknown","domain":"","country":"SR","name":"Pontbuiten","canton":"Paramaribo District","has_mx":false,"reason":"No MX records found"},{"bfs":"SR-048","district":"","provider":"unknown","domain":"","country":"SR","name":"Rainville","canton":"Paramaribo District","has_mx":false,"reason":"No MX records found"},{"bfs":"SR-049","osm_relation_id":13005707,"district":"","population":3076,"provider":"unknown","domain":"","country":"SR","name":"Sarakreek","canton":"Brokopondo District","has_mx":false,"reason":"No MX records found"},{"bfs":"SR-050","osm_relation_id":13026099,"district":"","provider":"unknown","domain":"","country":"SR","name":"Saramacca Polder","canton":"Wanica District","has_mx":false,"reason":"No MX records found"},{"bfs":"SR-051","district":"","provider":"unknown","domain":"","country":"SR","name":"Tamanredjo Ressort","canton":"Commewijne District","has_mx":false,"reason":"No MX records found"},{"bfs":"SR-052","osm_relation_id":13026432,"district":"","provider":"unknown","domain":"","country":"SR","name":"Tammenga","canton":"Paramaribo District","has_mx":false,"reason":"No MX records found"},{"bfs":"SR-053","osm_relation_id":13000345,"district":"","provider":"unknown","domain":"","country":"SR","name":"Tapanahony","canton":"Sipaliwini District","has_mx":false,"reason":"No MX records found"},{"bfs":"SR-054","osm_relation_id":13025345,"district":"","provider":"unknown","domain":"","country":"SR","name":"Tijgerkreek","canton":"Saramacca District","has_mx":false,"reason":"No MX records found"},{"bfs":"SR-055","osm_relation_id":12994995,"district":"","population":2150,"provider":"unknown","domain":"","country":"SR","name":"Totness","canton":"Coronie District","has_mx":false,"reason":"No MX records found"},{"bfs":"SR-056","district":"","provider":"unknown","domain":"","country":"SR","name":"Wageningen Ressort","canton":"Nickerie District","has_mx":false,"reason":"No MX records found"},{"bfs":"SR-057","osm_relation_id":13011763,"district":"","population":466,"provider":"unknown","domain":"","country":"SR","name":"Wanhatti","canton":"Marowijne District","has_mx":false,"reason":"No MX records found"},{"bfs":"SR-058","osm_relation_id":13024975,"district":"","provider":"unknown","domain":"","country":"SR","name":"Wayamboweg","canton":"Saramacca District","has_mx":false,"reason":"No MX records found"},{"bfs":"SR-059","osm_relation_id":13026308,"district":"","provider":"unknown","domain":"","country":"SR","name":"Weg naar Zee","canton":"Paramaribo District","has_mx":false,"reason":"No MX records found"},{"bfs":"SR-060","osm_relation_id":12995408,"district":"","population":19304,"provider":"unknown","domain":"","country":"SR","name":"Welgelegen","canton":"Coronie District","has_mx":false,"reason":"No MX records found"},{"bfs":"SR-061","osm_relation_id":13026384,"district":"","population":19304,"provider":"unknown","domain":"","country":"SR","name":"Welgelegen","canton":"Paramaribo District","has_mx":false,"reason":"No MX records found"},{"bfs":"SR-062","osm_relation_id":12995650,"district":"","provider":"unknown","domain":"","country":"SR","name":"Westelijke Polders","canton":"Nickerie District","has_mx":false,"reason":"No MX records found"},{"bfs":"SR-063","district":"","provider":"unknown","domain":"","country":"SR","name":"Zorg en Hoop Ressort","canton":"Paramaribo District","has_mx":false,"reason":"No MX records found"},{"bfs":"SR-064","osm_relation_id":13008690,"district":"","provider":"unknown","domain":"","country":"SR","name":"Zuid-Para","canton":"Para District","has_mx":false,"reason":"No MX records found"}]