[
  {
    "id": "HU-001",
    "name": "Ajka District",
    "country": "HU",
    "region": "Veszprém County",
    "domain": "",
    "osm_relation_id": 2376965
  },
  {
    "id": "HU-002",
    "name": "Aszód District",
    "country": "HU",
    "region": "Pest County",
    "domain": "",
    "osm_relation_id": 2376179
  },
  {
    "id": "HU-003",
    "name": "Baja District",
    "country": "HU",
    "region": "Bács-Kiskun County",
    "domain": "",
    "osm_relation_id": 2374268
  },
  {
    "id": "HU-004",
    "name": "Baktalórántháza District",
    "country": "HU",
    "region": "Szabolcs-Szatmár-Bereg County",
    "domain": "",
    "osm_relation_id": 2376334
  },
  {
    "id": "HU-005",
    "name": "Balassagyarmat District",
    "country": "HU",
    "region": "Nógrád County",
    "domain": "",
    "osm_relation_id": 2376127
  },
  {
    "id": "HU-006",
    "name": "Balatonalmádi District",
    "country": "HU",
    "region": "Veszprém County",
    "domain": "",
    "osm_relation_id": 2376975
  },
  {
    "id": "HU-007",
    "name": "Balatonfüred District",
    "country": "HU",
    "region": "Veszprém County",
    "domain": "",
    "osm_relation_id": 2376985
  },
  {
    "id": "HU-008",
    "name": "Balmazújváros District",
    "country": "HU",
    "region": "Hajdú-Bihar County",
    "domain": "",
    "osm_relation_id": 2376014
  },
  {
    "id": "HU-009",
    "name": "Barcs District",
    "country": "HU",
    "region": "Somogy County",
    "domain": "",
    "osm_relation_id": 2376257
  },
  {
    "id": "HU-010",
    "name": "Berettyóújfalu District",
    "country": "HU",
    "region": "Hajdú-Bihar County",
    "domain": "",
    "osm_relation_id": 2376016
  },
  {
    "id": "HU-011",
    "name": "Bicske District",
    "country": "HU",
    "region": "Fejér County",
    "domain": "",
    "osm_relation_id": 2375779
  },
  {
    "id": "HU-012",
    "name": "Bonyhád District",
    "country": "HU",
    "region": "Tolna County",
    "domain": "",
    "osm_relation_id": 2376625
  },
  {
    "id": "HU-013",
    "name": "Budakeszi District",
    "country": "HU",
    "region": "Pest County",
    "domain": "",
    "osm_relation_id": 2376186
  },
  {
    "id": "HU-014",
    "name": "Bácsalmás District",
    "country": "HU",
    "region": "Bács-Kiskun County",
    "domain": "",
    "osm_relation_id": 2374278
  },
  {
    "id": "HU-015",
    "name": "Bátonyterenye District",
    "country": "HU",
    "region": "Nógrád County",
    "domain": "",
    "osm_relation_id": 2376135
  },
  {
    "id": "HU-016",
    "name": "Békés District",
    "country": "HU",
    "region": "Békés County",
    "domain": "",
    "osm_relation_id": 2374330
  },
  {
    "id": "HU-017",
    "name": "Békéscsaba District",
    "country": "HU",
    "region": "Békés County",
    "domain": "",
    "osm_relation_id": 2374436
  },
  {
    "id": "HU-018",
    "name": "Bélapátfalva District",
    "country": "HU",
    "region": "Heves County",
    "domain": "",
    "osm_relation_id": 2376056
  },
  {
    "id": "HU-019",
    "name": "Bóly District",
    "country": "HU",
    "region": "Baranya County",
    "domain": "",
    "osm_relation_id": 2374168
  },
  {
    "id": "HU-020",
    "name": "Cegléd District",
    "country": "HU",
    "region": "Pest County",
    "domain": "",
    "osm_relation_id": 2376201
  },
  {
    "id": "HU-021",
    "name": "Celldömölk District",
    "country": "HU",
    "region": "Vas County",
    "domain": "",
    "osm_relation_id": 2376679
  },
  {
    "id": "HU-022",
    "name": "Cigánd District",
    "country": "HU",
    "region": "Borsod-Abaúj-Zemplén County",
    "domain": "",
    "osm_relation_id": 2374641
  },
  {
    "id": "HU-023",
    "name": "Csenger District",
    "country": "HU",
    "region": "Szabolcs-Szatmár-Bereg County",
    "domain": "",
    "osm_relation_id": 2376337
  },
  {
    "id": "HU-024",
    "name": "Csongrád District",
    "country": "HU",
    "region": "Csongrád-Csanád County",
    "domain": "",
    "osm_relation_id": 2374772
  },
  {
    "id": "HU-025",
    "name": "Csorna District",
    "country": "HU",
    "region": "Győr-Moson-Sopron County",
    "domain": "",
    "osm_relation_id": 2375881
  },
  {
    "id": "HU-026",
    "name": "Csurgó District",
    "country": "HU",
    "region": "Somogy County",
    "domain": "",
    "osm_relation_id": 2376274
  },
  {
    "id": "HU-027",
    "name": "Dabas District",
    "country": "HU",
    "region": "Pest County",
    "domain": "",
    "osm_relation_id": 2376205
  },
  {
    "id": "HU-028",
    "name": "Debrecen District",
    "country": "HU",
    "region": "Hajdú-Bihar County",
    "domain": "",
    "osm_relation_id": 2376017
  },
  {
    "id": "HU-029",
    "name": "Derecske District",
    "country": "HU",
    "region": "Hajdú-Bihar County",
    "domain": "",
    "osm_relation_id": 2376023
  },
  {
    "id": "HU-030",
    "name": "Devecser District",
    "country": "HU",
    "region": "Veszprém County",
    "domain": "",
    "osm_relation_id": 2376990
  },
  {
    "id": "HU-031",
    "name": "Dombóvár District",
    "country": "HU",
    "region": "Tolna County",
    "domain": "",
    "osm_relation_id": 2376632
  },
  {
    "id": "HU-032",
    "name": "Dunakeszi District",
    "country": "HU",
    "region": "Pest County",
    "domain": "",
    "osm_relation_id": 2376206
  },
  {
    "id": "HU-033",
    "name": "Dunaújváros District",
    "country": "HU",
    "region": "Fejér County",
    "domain": "",
    "osm_relation_id": 2375782
  },
  {
    "id": "HU-034",
    "name": "Edelény District",
    "country": "HU",
    "region": "Borsod-Abaúj-Zemplén County",
    "domain": "",
    "osm_relation_id": 2374652
  },
  {
    "id": "HU-035",
    "name": "Eger District",
    "country": "HU",
    "region": "Heves County",
    "domain": "",
    "osm_relation_id": 2376060
  },
  {
    "id": "HU-036",
    "name": "Encs District",
    "country": "HU",
    "region": "Borsod-Abaúj-Zemplén County",
    "domain": "",
    "osm_relation_id": 2374664
  },
  {
    "id": "HU-037",
    "name": "Enying District",
    "country": "HU",
    "region": "Fejér County",
    "domain": "",
    "osm_relation_id": 2375785
  },
  {
    "id": "HU-038",
    "name": "Esztergom District",
    "country": "HU",
    "region": "Komárom-Esztergom County",
    "domain": "kormanyhivatal.hu",
    "osm_relation_id": 2376099
  },
  {
    "id": "HU-039",
    "name": "Fehérgyarmat District",
    "country": "HU",
    "region": "Szabolcs-Szatmár-Bereg County",
    "domain": "",
    "osm_relation_id": 2376340
  },
  {
    "id": "HU-040",
    "name": "Fonyód District",
    "country": "HU",
    "region": "Somogy County",
    "domain": "",
    "osm_relation_id": 2376281
  },
  {
    "id": "HU-041",
    "name": "Füzesabony District",
    "country": "HU",
    "region": "Heves County",
    "domain": "",
    "osm_relation_id": 2376061
  },
  {
    "id": "HU-042",
    "name": "Gyomaendrőd District",
    "country": "HU",
    "region": "Békés County",
    "domain": "",
    "osm_relation_id": 2374440
  },
  {
    "id": "HU-043",
    "name": "Gyula District",
    "country": "HU",
    "region": "Békés County",
    "domain": "",
    "osm_relation_id": 2374443
  },
  {
    "id": "HU-044",
    "name": "Gyál District",
    "country": "HU",
    "region": "Pest County",
    "domain": "",
    "osm_relation_id": 2376216
  },
  {
    "id": "HU-045",
    "name": "Gyöngyös District",
    "country": "HU",
    "region": "Heves County",
    "domain": "",
    "osm_relation_id": 2376062
  },
  {
    "id": "HU-046",
    "name": "Győr District",
    "country": "HU",
    "region": "Győr-Moson-Sopron County",
    "domain": "",
    "osm_relation_id": 2375909
  },
  {
    "id": "HU-047",
    "name": "Gárdony District",
    "country": "HU",
    "region": "Fejér County",
    "domain": "",
    "osm_relation_id": 2375790
  },
  {
    "id": "HU-048",
    "name": "Gödöllő District",
    "country": "HU",
    "region": "Pest County",
    "domain": "",
    "osm_relation_id": 2376213
  },
  {
    "id": "HU-049",
    "name": "Gönc District",
    "country": "HU",
    "region": "Borsod-Abaúj-Zemplén County",
    "domain": "",
    "osm_relation_id": 2374675
  },
  {
    "id": "HU-050",
    "name": "Hajdúböszörmény District",
    "country": "HU",
    "region": "Hajdú-Bihar County",
    "domain": "",
    "osm_relation_id": 2376026
  },
  {
    "id": "HU-051",
    "name": "Hajdúhadház District",
    "country": "HU",
    "region": "Hajdú-Bihar County",
    "domain": "",
    "osm_relation_id": 2376027
  },
  {
    "id": "HU-052",
    "name": "Hajdúnánás District",
    "country": "HU",
    "region": "Hajdú-Bihar County",
    "domain": "",
    "osm_relation_id": 2376029
  },
  {
    "id": "HU-053",
    "name": "Hajdúszoboszló District",
    "country": "HU",
    "region": "Hajdú-Bihar County",
    "domain": "",
    "osm_relation_id": 2376034
  },
  {
    "id": "HU-054",
    "name": "Hatvan District",
    "country": "HU",
    "region": "Heves County",
    "domain": "",
    "osm_relation_id": 2376065
  },
  {
    "id": "HU-055",
    "name": "Hegyhát District",
    "country": "HU",
    "region": "Baranya County",
    "domain": "",
    "osm_relation_id": 2374236
  },
  {
    "id": "HU-056",
    "name": "Heves District",
    "country": "HU",
    "region": "Heves County",
    "domain": "",
    "osm_relation_id": 2376066
  },
  {
    "id": "HU-057",
    "name": "Hódmezővásárhely District",
    "country": "HU",
    "region": "Csongrád-Csanád County",
    "domain": "",
    "osm_relation_id": 2374823
  },
  {
    "id": "HU-058",
    "name": "Ibrány District",
    "country": "HU",
    "region": "Szabolcs-Szatmár-Bereg County",
    "domain": "",
    "osm_relation_id": 2376349
  },
  {
    "id": "HU-059",
    "name": "Jánoshalma District",
    "country": "HU",
    "region": "Bács-Kiskun County",
    "domain": "",
    "osm_relation_id": 2374281
  },
  {
    "id": "HU-060",
    "name": "Jászapáti District",
    "country": "HU",
    "region": "Jász-Nagykun-Szolnok County",
    "domain": "",
    "osm_relation_id": 2376079
  },
  {
    "id": "HU-061",
    "name": "Jászberény District",
    "country": "HU",
    "region": "Jász-Nagykun-Szolnok County",
    "domain": "",
    "osm_relation_id": 2376081
  },
  {
    "id": "HU-062",
    "name": "Kalocsa District",
    "country": "HU",
    "region": "Bács-Kiskun County",
    "domain": "",
    "osm_relation_id": 2374285
  },
  {
    "id": "HU-063",
    "name": "Kaposvár District",
    "country": "HU",
    "region": "Somogy County",
    "domain": "",
    "osm_relation_id": 2376283
  },
  {
    "id": "HU-064",
    "name": "Kapuvár District",
    "country": "HU",
    "region": "Győr-Moson-Sopron County",
    "domain": "",
    "osm_relation_id": 2375937
  },
  {
    "id": "HU-065",
    "name": "Karcag District",
    "country": "HU",
    "region": "Jász-Nagykun-Szolnok County",
    "domain": "",
    "osm_relation_id": 2376084
  },
  {
    "id": "HU-066",
    "name": "Kazincbarcika District",
    "country": "HU",
    "region": "Borsod-Abaúj-Zemplén County",
    "domain": "",
    "osm_relation_id": 2374680
  },
  {
    "id": "HU-067",
    "name": "Kecskemét District",
    "country": "HU",
    "region": "Bács-Kiskun County",
    "domain": "",
    "osm_relation_id": 2374286
  },
  {
    "id": "HU-068",
    "name": "Kemecse District",
    "country": "HU",
    "region": "Szabolcs-Szatmár-Bereg County",
    "domain": "",
    "osm_relation_id": 2376351
  },
  {
    "id": "HU-069",
    "name": "Keszthely District",
    "country": "HU",
    "region": "Zala County",
    "domain": "",
    "osm_relation_id": 2377058
  },
  {
    "id": "HU-070",
    "name": "Kisbér District",
    "country": "HU",
    "region": "Komárom-Esztergom County",
    "domain": "kormanyhivatal.hu",
    "osm_relation_id": 2376103
  },
  {
    "id": "HU-071",
    "name": "Kiskunfélegyháza District",
    "country": "HU",
    "region": "Bács-Kiskun County",
    "domain": "",
    "osm_relation_id": 2374302
  },
  {
    "id": "HU-072",
    "name": "Kiskunhalas District",
    "country": "HU",
    "region": "Bács-Kiskun County",
    "domain": "",
    "osm_relation_id": 2374305
  },
  {
    "id": "HU-073",
    "name": "Kiskunmajsa District",
    "country": "HU",
    "region": "Bács-Kiskun County",
    "domain": "",
    "osm_relation_id": 2374322
  },
  {
    "id": "HU-074",
    "name": "Kiskőrös District",
    "country": "HU",
    "region": "Bács-Kiskun County",
    "domain": "",
    "osm_relation_id": 2374296
  },
  {
    "id": "HU-075",
    "name": "Kistelek District",
    "country": "HU",
    "region": "Csongrád-Csanád County",
    "domain": "",
    "osm_relation_id": 2374827
  },
  {
    "id": "HU-076",
    "name": "Kisvárda District",
    "country": "HU",
    "region": "Szabolcs-Szatmár-Bereg County",
    "domain": "",
    "osm_relation_id": 2376365
  },
  {
    "id": "HU-077",
    "name": "Komló District",
    "country": "HU",
    "region": "Baranya County",
    "domain": "",
    "osm_relation_id": 2374169
  },
  {
    "id": "HU-078",
    "name": "Komárom District",
    "country": "HU",
    "region": "Komárom-Esztergom County",
    "domain": "kormanyhivatal.hu",
    "osm_relation_id": 2376107
  },
  {
    "id": "HU-079",
    "name": "Kunhegyes District",
    "country": "HU",
    "region": "Jász-Nagykun-Szolnok County",
    "domain": "",
    "osm_relation_id": 2376090
  },
  {
    "id": "HU-080",
    "name": "Kunszentmiklós District",
    "country": "HU",
    "region": "Bács-Kiskun County",
    "domain": "",
    "osm_relation_id": 2374326
  },
  {
    "id": "HU-081",
    "name": "Kunszentmárton District",
    "country": "HU",
    "region": "Jász-Nagykun-Szolnok County",
    "domain": "",
    "osm_relation_id": 2376092
  },
  {
    "id": "HU-082",
    "name": "Körmend District",
    "country": "HU",
    "region": "Vas County",
    "domain": "",
    "osm_relation_id": 2376748
  },
  {
    "id": "HU-083",
    "name": "Kőszeg District",
    "country": "HU",
    "region": "Vas County",
    "domain": "",
    "osm_relation_id": 2376755
  },
  {
    "id": "HU-084",
    "name": "Lenti District",
    "country": "HU",
    "region": "Zala County",
    "domain": "",
    "osm_relation_id": 2377063
  },
  {
    "id": "HU-085",
    "name": "Letenye District",
    "country": "HU",
    "region": "Zala County",
    "domain": "",
    "osm_relation_id": 2377090
  },
  {
    "id": "HU-086",
    "name": "Makó District",
    "country": "HU",
    "region": "Csongrád-Csanád County",
    "domain": "",
    "osm_relation_id": 2374832
  },
  {
    "id": "HU-087",
    "name": "Marcali District",
    "country": "HU",
    "region": "Somogy County",
    "domain": "",
    "osm_relation_id": 2376284
  },
  {
    "id": "HU-088",
    "name": "Martonvásár District",
    "country": "HU",
    "region": "Fejér County",
    "domain": "",
    "osm_relation_id": 2375848
  },
  {
    "id": "HU-089",
    "name": "Mezőcsát District",
    "country": "HU",
    "region": "Borsod-Abaúj-Zemplén County",
    "domain": "",
    "osm_relation_id": 2374683
  },
  {
    "id": "HU-090",
    "name": "Mezőkovácsháza District",
    "country": "HU",
    "region": "Békés County",
    "domain": "",
    "osm_relation_id": 2374447
  },
  {
    "id": "HU-091",
    "name": "Mezőkövesd District",
    "country": "HU",
    "region": "Borsod-Abaúj-Zemplén County",
    "domain": "",
    "osm_relation_id": 2374698
  },
  {
    "id": "HU-092",
    "name": "Mezőtúr District",
    "country": "HU",
    "region": "Jász-Nagykun-Szolnok County",
    "domain": "",
    "osm_relation_id": 2376093
  },
  {
    "id": "HU-093",
    "name": "Miskolc District",
    "country": "HU",
    "region": "Borsod-Abaúj-Zemplén County",
    "domain": "",
    "osm_relation_id": 2374713
  },
  {
    "id": "HU-094",
    "name": "Mohács District",
    "country": "HU",
    "region": "Baranya County",
    "domain": "",
    "osm_relation_id": 2374219
  },
  {
    "id": "HU-095",
    "name": "Monor District",
    "country": "HU",
    "region": "Pest County",
    "domain": "",
    "osm_relation_id": 2376220
  },
  {
    "id": "HU-096",
    "name": "Mosonmagyaróvár District",
    "country": "HU",
    "region": "Győr-Moson-Sopron County",
    "domain": "",
    "osm_relation_id": 2375986
  },
  {
    "id": "HU-097",
    "name": "Mátészalka District",
    "country": "HU",
    "region": "Szabolcs-Szatmár-Bereg County",
    "domain": "",
    "osm_relation_id": 2376367
  },
  {
    "id": "HU-098",
    "name": "Mór District",
    "country": "HU",
    "region": "Fejér County",
    "domain": "",
    "osm_relation_id": 2375851
  },
  {
    "id": "HU-099",
    "name": "Mórahalom District",
    "country": "HU",
    "region": "Csongrád-Csanád County",
    "domain": "",
    "osm_relation_id": 2374833
  },
  {
    "id": "HU-100",
    "name": "Nagyatád District",
    "country": "HU",
    "region": "Somogy County",
    "domain": "",
    "osm_relation_id": 2376312
  },
  {
    "id": "HU-101",
    "name": "Nagykanizsa District",
    "country": "HU",
    "region": "Zala County",
    "domain": "",
    "osm_relation_id": 2377098
  },
  {
    "id": "HU-102",
    "name": "Nagykálló District",
    "country": "HU",
    "region": "Szabolcs-Szatmár-Bereg County",
    "domain": "",
    "osm_relation_id": 2376369
  },
  {
    "id": "HU-103",
    "name": "Nagykáta District",
    "country": "HU",
    "region": "Pest County",
    "domain": "",
    "osm_relation_id": 2376221
  },
  {
    "id": "HU-104",
    "name": "Nagykőrös District",
    "country": "HU",
    "region": "Pest County",
    "domain": "",
    "osm_relation_id": 2376225
  },
  {
    "id": "HU-105",
    "name": "Nyíradony District",
    "country": "HU",
    "region": "Hajdú-Bihar County",
    "domain": "",
    "osm_relation_id": 2376043
  },
  {
    "id": "HU-106",
    "name": "Nyírbátor District",
    "country": "HU",
    "region": "Szabolcs-Szatmár-Bereg County",
    "domain": "",
    "osm_relation_id": 2376372
  },
  {
    "id": "HU-107",
    "name": "Nyíregyháza District",
    "country": "HU",
    "region": "Szabolcs-Szatmár-Bereg County",
    "domain": "",
    "osm_relation_id": 2376374
  },
  {
    "id": "HU-108",
    "name": "Orosháza District",
    "country": "HU",
    "region": "Békés County",
    "domain": "",
    "osm_relation_id": 2374452
  },
  {
    "id": "HU-109",
    "name": "Oroszlány District",
    "country": "HU",
    "region": "Komárom-Esztergom County",
    "domain": "",
    "osm_relation_id": 2376110
  },
  {
    "id": "HU-110",
    "name": "Paks District",
    "country": "HU",
    "region": "Tolna County",
    "domain": "",
    "osm_relation_id": 2376640
  },
  {
    "id": "HU-111",
    "name": "Pannonhalma District",
    "country": "HU",
    "region": "Győr-Moson-Sopron County",
    "domain": "",
    "osm_relation_id": 2375992
  },
  {
    "id": "HU-112",
    "name": "Pilisvörösvár District",
    "country": "HU",
    "region": "Pest County",
    "domain": "",
    "osm_relation_id": 2376230
  },
  {
    "id": "HU-113",
    "name": "Putnok District",
    "country": "HU",
    "region": "Borsod-Abaúj-Zemplén County",
    "domain": "",
    "osm_relation_id": 2374720
  },
  {
    "id": "HU-114",
    "name": "Pápa District",
    "country": "HU",
    "region": "Veszprém County",
    "domain": "",
    "osm_relation_id": 2376998
  },
  {
    "id": "HU-115",
    "name": "Pásztó District",
    "country": "HU",
    "region": "Nógrád County",
    "domain": "",
    "osm_relation_id": 2376140
  },
  {
    "id": "HU-116",
    "name": "Pécs District",
    "country": "HU",
    "region": "Baranya County",
    "domain": "",
    "osm_relation_id": 2374220
  },
  {
    "id": "HU-117",
    "name": "Pécsvárad District",
    "country": "HU",
    "region": "Baranya County",
    "domain": "",
    "osm_relation_id": 2374228
  },
  {
    "id": "HU-118",
    "name": "Pétervására District",
    "country": "HU",
    "region": "Heves County",
    "domain": "",
    "osm_relation_id": 2376076
  },
  {
    "id": "HU-119",
    "name": "Püspökladány District",
    "country": "HU",
    "region": "Hajdú-Bihar County",
    "domain": "",
    "osm_relation_id": 2376053
  },
  {
    "id": "HU-120",
    "name": "Ráckeve District",
    "country": "HU",
    "region": "Pest County",
    "domain": "",
    "osm_relation_id": 2376233
  },
  {
    "id": "HU-121",
    "name": "Rétság District",
    "country": "HU",
    "region": "Nógrád County",
    "domain": "",
    "osm_relation_id": 2376143
  },
  {
    "id": "HU-122",
    "name": "Salgótarján District",
    "country": "HU",
    "region": "Nógrád County",
    "domain": "",
    "osm_relation_id": 2376147
  },
  {
    "id": "HU-123",
    "name": "Sarkad District",
    "country": "HU",
    "region": "Békés County",
    "domain": "",
    "osm_relation_id": 2374456
  },
  {
    "id": "HU-124",
    "name": "Sellye District",
    "country": "HU",
    "region": "Baranya County",
    "domain": "",
    "osm_relation_id": 2374243
  },
  {
    "id": "HU-125",
    "name": "Siklós District",
    "country": "HU",
    "region": "Baranya County",
    "domain": "",
    "osm_relation_id": 2374254
  },
  {
    "id": "HU-126",
    "name": "Siófok District",
    "country": "HU",
    "region": "Somogy County",
    "domain": "",
    "osm_relation_id": 2376318
  },
  {
    "id": "HU-127",
    "name": "Sopron District",
    "country": "HU",
    "region": "Győr-Moson-Sopron County",
    "domain": "",
    "osm_relation_id": 2376007
  },
  {
    "id": "HU-128",
    "name": "Szarvas District",
    "country": "HU",
    "region": "Békés County",
    "domain": "",
    "osm_relation_id": 2374463
  },
  {
    "id": "HU-129",
    "name": "Szeged District",
    "country": "HU",
    "region": "Csongrád-Csanád County",
    "domain": "",
    "osm_relation_id": 2374836
  },
  {
    "id": "HU-130",
    "name": "Szeghalom District",
    "country": "HU",
    "region": "Békés County",
    "domain": "",
    "osm_relation_id": 2374476
  },
  {
    "id": "HU-131",
    "name": "Szekszárd District",
    "country": "HU",
    "region": "Tolna County",
    "domain": "",
    "osm_relation_id": 2376648
  },
  {
    "id": "HU-132",
    "name": "Szentendre District",
    "country": "HU",
    "region": "Pest County",
    "domain": "",
    "osm_relation_id": 2376234
  },
  {
    "id": "HU-133",
    "name": "Szentes District",
    "country": "HU",
    "region": "Csongrád-Csanád County",
    "domain": "",
    "osm_relation_id": 2374837
  },
  {
    "id": "HU-134",
    "name": "Szentgotthárd District",
    "country": "HU",
    "region": "Vas County",
    "domain": "",
    "osm_relation_id": 2376872
  },
  {
    "id": "HU-135",
    "name": "Szentlőrinc District",
    "country": "HU",
    "region": "Baranya County",
    "domain": "",
    "osm_relation_id": 2374257
  },
  {
    "id": "HU-136",
    "name": "Szerencs District",
    "country": "HU",
    "region": "Borsod-Abaúj-Zemplén County",
    "domain": "",
    "osm_relation_id": 2374753
  },
  {
    "id": "HU-137",
    "name": "Szigetszentmiklós District",
    "country": "HU",
    "region": "Pest County",
    "domain": "",
    "osm_relation_id": 2376238
  },
  {
    "id": "HU-138",
    "name": "Szigetvár District",
    "country": "HU",
    "region": "Baranya County",
    "domain": "",
    "osm_relation_id": 2374264
  },
  {
    "id": "HU-139",
    "name": "Szikszó District",
    "country": "HU",
    "region": "Borsod-Abaúj-Zemplén County",
    "domain": "",
    "osm_relation_id": 2374761
  },
  {
    "id": "HU-140",
    "name": "Szob District",
    "country": "HU",
    "region": "Pest County",
    "domain": "",
    "osm_relation_id": 2376240
  },
  {
    "id": "HU-141",
    "name": "Szolnok District",
    "country": "HU",
    "region": "Jász-Nagykun-Szolnok County",
    "domain": "",
    "osm_relation_id": 2376095
  },
  {
    "id": "HU-142",
    "name": "Szombathely District",
    "country": "HU",
    "region": "Vas County",
    "domain": "",
    "osm_relation_id": 2376926
  },
  {
    "id": "HU-143",
    "name": "Szécsény District",
    "country": "HU",
    "region": "Nógrád County",
    "domain": "",
    "osm_relation_id": 2376149
  },
  {
    "id": "HU-144",
    "name": "Székesfehérvár District",
    "country": "HU",
    "region": "Fejér County",
    "domain": "",
    "osm_relation_id": 2375878
  },
  {
    "id": "HU-145",
    "name": "Sárbogárd District",
    "country": "HU",
    "region": "Fejér County",
    "domain": "",
    "osm_relation_id": 2375871
  },
  {
    "id": "HU-146",
    "name": "Sárospatak District",
    "country": "HU",
    "region": "Borsod-Abaúj-Zemplén County",
    "domain": "",
    "osm_relation_id": 2374741
  },
  {
    "id": "HU-147",
    "name": "Sárvár District",
    "country": "HU",
    "region": "Vas County",
    "domain": "",
    "osm_relation_id": 2376840
  },
  {
    "id": "HU-148",
    "name": "Sátoraljaújhely District",
    "country": "HU",
    "region": "Borsod-Abaúj-Zemplén County",
    "domain": "",
    "osm_relation_id": 2374748
  },
  {
    "id": "HU-149",
    "name": "Sümeg District",
    "country": "HU",
    "region": "Veszprém County",
    "domain": "",
    "osm_relation_id": 2377001
  },
  {
    "id": "HU-150",
    "name": "Tab District",
    "country": "HU",
    "region": "Somogy County",
    "domain": "",
    "osm_relation_id": 2376330
  },
  {
    "id": "HU-151",
    "name": "Tamási District",
    "country": "HU",
    "region": "Tolna County",
    "domain": "",
    "osm_relation_id": 2376652
  },
  {
    "id": "HU-152",
    "name": "Tapolca District",
    "country": "HU",
    "region": "Veszprém County",
    "domain": "",
    "osm_relation_id": 2377009
  },
  {
    "id": "HU-153",
    "name": "Tata District",
    "country": "HU",
    "region": "Komárom-Esztergom County",
    "domain": "",
    "osm_relation_id": 2376113
  },
  {
    "id": "HU-154",
    "name": "Tatabánya District",
    "country": "HU",
    "region": "Komárom-Esztergom County",
    "domain": "",
    "osm_relation_id": 2376120
  },
  {
    "id": "HU-155",
    "name": "Tiszafüred District",
    "country": "HU",
    "region": "Jász-Nagykun-Szolnok County",
    "domain": "",
    "osm_relation_id": 2376096
  },
  {
    "id": "HU-156",
    "name": "Tiszakécske District",
    "country": "HU",
    "region": "Bács-Kiskun County",
    "domain": "",
    "osm_relation_id": 2374327
  },
  {
    "id": "HU-157",
    "name": "Tiszavasvári District",
    "country": "HU",
    "region": "Szabolcs-Szatmár-Bereg County",
    "domain": "",
    "osm_relation_id": 2376378
  },
  {
    "id": "HU-158",
    "name": "Tiszaújváros District",
    "country": "HU",
    "region": "Borsod-Abaúj-Zemplén County",
    "domain": "",
    "osm_relation_id": 2374763
  },
  {
    "id": "HU-159",
    "name": "Tokaj District",
    "country": "HU",
    "region": "Borsod-Abaúj-Zemplén County",
    "domain": "",
    "osm_relation_id": 2374767
  },
  {
    "id": "HU-160",
    "name": "Tolna District",
    "country": "HU",
    "region": "Tolna County",
    "domain": "",
    "osm_relation_id": 2376655
  },
  {
    "id": "HU-161",
    "name": "Tét District",
    "country": "HU",
    "region": "Győr-Moson-Sopron County",
    "domain": "",
    "osm_relation_id": 2376010
  },
  {
    "id": "HU-162",
    "name": "Törökszentmiklós District",
    "country": "HU",
    "region": "Jász-Nagykun-Szolnok County",
    "domain": "",
    "osm_relation_id": 2376097
  },
  {
    "id": "HU-163",
    "name": "Vasvár District",
    "country": "HU",
    "region": "Vas County",
    "domain": "",
    "osm_relation_id": 2376929
  },
  {
    "id": "HU-164",
    "name": "Vecsés District",
    "country": "HU",
    "region": "Pest County",
    "domain": "",
    "osm_relation_id": 2376243
  },
  {
    "id": "HU-165",
    "name": "Veszprém District",
    "country": "HU",
    "region": "Veszprém County",
    "domain": "",
    "osm_relation_id": 2377042
  },
  {
    "id": "HU-166",
    "name": "Vác District",
    "country": "HU",
    "region": "Pest County",
    "domain": "",
    "osm_relation_id": 2376241
  },
  {
    "id": "HU-167",
    "name": "Várpalota District",
    "country": "HU",
    "region": "Veszprém County",
    "domain": "",
    "osm_relation_id": 2377013
  },
  {
    "id": "HU-168",
    "name": "Vásárosnamény District",
    "country": "HU",
    "region": "Szabolcs-Szatmár-Bereg County",
    "domain": "",
    "osm_relation_id": 2376382
  },
  {
    "id": "HU-169",
    "name": "Zalaegerszeg District",
    "country": "HU",
    "region": "Zala County",
    "domain": "",
    "osm_relation_id": 2377111
  },
  {
    "id": "HU-170",
    "name": "Zalaszentgrót District",
    "country": "HU",
    "region": "Zala County",
    "domain": "kormanyhivatalok.hu",
    "osm_relation_id": 2377130
  },
  {
    "id": "HU-171",
    "name": "Zirc District",
    "country": "HU",
    "region": "Veszprém County",
    "domain": "",
    "osm_relation_id": 2377047
  },
  {
    "id": "HU-172",
    "name": "Záhony District",
    "country": "HU",
    "region": "Szabolcs-Szatmár-Bereg County",
    "domain": "",
    "osm_relation_id": 2376398
  },
  {
    "id": "HU-173",
    "name": "Érd District",
    "country": "HU",
    "region": "Pest County",
    "domain": "",
    "osm_relation_id": 2376210
  },
  {
    "id": "HU-174",
    "name": "Ózd District",
    "country": "HU",
    "region": "Borsod-Abaúj-Zemplén County",
    "domain": "",
    "osm_relation_id": 2374714
  }
]